py3o.renderserver-0.5.2-py2.7-nspkg.pth
ooservice/service-setup.py
ooservice/__init__.py
ooservice/setup-ooservice.py
ooservice/ooservice.py
py3o/renderserver/server.py
py3o/renderserver/service.py
py3o/renderserver/__init__.py
py3o.renderserver-0.5.2.dist-info/DESCRIPTION.rst
py3o.renderserver-0.5.2.dist-info/top_level.txt
py3o.renderserver-0.5.2.dist-info/zip-safe
py3o.renderserver-0.5.2.dist-info/METADATA
py3o.renderserver-0.5.2.dist-info/RECORD
py3o.renderserver-0.5.2.dist-info/WHEEL
py3o.renderserver-0.5.2.dist-info/metadata.json
py3o.renderserver-0.5.2.dist-info/namespace_packages.txt
py3o.renderserver-0.5.2.dist-info/entry_points.txt
