Metadata-Version: 2.0
Name: py3o.renderserver
Version: 0.5.2
Summary: An easy solution to transform libreoffice/openoffice documents to supported formats
Home-page: http://bitbucket.org/faide/py3o.renderserver
Author: Florent Aide
Author-email: florent.aide@gmail.com
License: BSD License
Keywords: LibreOffice OpenOffice PDF
Platform: UNKNOWN
Classifier: Programming Language :: Python
Classifier: Topic :: Software Development :: Libraries :: Python Modules
Requires-Dist: setuptools
Requires-Dist: pyf.station (>=2.0.1)
Requires-Dist: pyjon.utils (>=0.6)
Requires-Dist: py3o.formats
Requires-Dist: py3o.renderers.juno (>=0.8.1)
